CHANGES.txt
MANIFEST.in
requirements.txt
setup.cfg
setup.py
csgoogleanalytics/__init__.py
csgoogleanalytics/admin.py
csgoogleanalytics/models.py
csgoogleanalytics/readme.md
csgoogleanalytics/utils.py
csgoogleanalytics/validators.py
csgoogleanalytics.egg-info/PKG-INFO
csgoogleanalytics.egg-info/SOURCES.txt
csgoogleanalytics.egg-info/dependency_links.txt
csgoogleanalytics.egg-info/not-zip-safe
csgoogleanalytics.egg-info/requires.txt
csgoogleanalytics.egg-info/top_level.txt
csgoogleanalytics/management/__init__.py
csgoogleanalytics/management/commands/__init__.py
csgoogleanalytics/management/commands/update_analytics.py
csgoogleanalytics/management/commands/update_pages.py
csgoogleanalytics/migrations/0001_initial.py
csgoogleanalytics/migrations/0002_remove_analyticsprofile_credentials_and_more.py
csgoogleanalytics/migrations/__init__.py
csgoogleanalytics/templates/csgoogleanalytics/select_analytics_property.html