Metadata-Version: 2.1
Name: csgoogleanalytics
Version: 2.7
Summary: Google analyticseko gure webguneko datuak hileka edo asteka jasotzeko tresna
Home-page: 
Author: Jatsu Argarate
Author-email: jargarate@codesyntax.com
Requires-Dist: django-object-actions==4.1.0
